flask_smores.py
Flask_Smores-0.2.1.dist-info/DESCRIPTION.rst
Flask_Smores-0.2.1.dist-info/METADATA
Flask_Smores-0.2.1.dist-info/RECORD
Flask_Smores-0.2.1.dist-info/WHEEL
Flask_Smores-0.2.1.dist-info/metadata.json
Flask_Smores-0.2.1.dist-info/top_level.txt
